hidir/__init__.py
hidir/exceptions.py
hidir/handler.py
hidir/py.typed
hidir/utils.py
hidir/version.py
hidir-0.0.2.dist-info/LICENSE
hidir-0.0.2.dist-info/METADATA
hidir-0.0.2.dist-info/WHEEL
hidir-0.0.2.dist-info/top_level.txt
hidir-0.0.2.dist-info/RECORD
